{
  "cycle_timestamp": "2026-04-05T17-50-45Z",
  "cycle_start_utc": "2026-04-05T17:30:00Z",
  "cycle_end_utc": "2026-04-05T17:55:00Z",
  "cycle_duration_minutes": 25,
  "text_requests_used": 14,
  "text_requests_note": "MiniMax search API calls only; text generation within this session not tracked separately",
  "tts_requests_used": 0,
  "tts_requests_note": "TTS scripts generated but not yet converted to audio (user can run TTS conversion separately)",
  "image_requests_used": 0,
  "image_requests_note": "Image directions generated but not yet rendered; user can use these directions with image generation tools",
  "minimax_search_calls": 14,
  "search_buckets_covered": [
    "frontier_models",
    "agents",
    "funding",
    "open_source",
    "developer_tools",
    "enterprise",
    "pricing"
  ],
  "signals_collected": 82,
  "clusters_formed": 18,
  "themes_ranked": 15,
  "top3_fully_analyzed": 3,
  "notes": "Single-cycle manual mode (Mode B) test run. Signals collected via MiniMax search across 7 buckets. Top 15 ranked and Top 3 deeply analyzed using 4 perspectives. Posts, TTS scripts, and image directions generated. GitHub persistence next."
}
